nse50bse30.py
nse50bse30-0.0.3.dist-info/LICENCE.txt
nse50bse30-0.0.3.dist-info/METADATA
nse50bse30-0.0.3.dist-info/WHEEL
nse50bse30-0.0.3.dist-info/top_level.txt
nse50bse30-0.0.3.dist-info/RECORD
